bin/__init__.py
bin/git_fetch_gitignore.py
fetch_gitignore/__init__.py
fetch_gitignore/gitignore.py
git_fetch_gitignore-0.0.1.data/scripts/git_fetch_gitignore.py
git_fetch_gitignore-0.0.1.dist-info/DESCRIPTION.rst
git_fetch_gitignore-0.0.1.dist-info/METADATA
git_fetch_gitignore-0.0.1.dist-info/RECORD
git_fetch_gitignore-0.0.1.dist-info/WHEEL
git_fetch_gitignore-0.0.1.dist-info/entry_points.txt
git_fetch_gitignore-0.0.1.dist-info/metadata.json
git_fetch_gitignore-0.0.1.dist-info/top_level.txt
usr/local/man/man1/git-fetch-gitignore.1/git-fetch-gitignore.1
