Metadata-Version: 2.0
Name: git-fetch-gitignore
Version: 0.0.1
Summary: Fetch .gitignore files from GitHub
Home-page: https://github.com/clickyotomy/git-fetch-gitignore
Author: Srinidhi Kaushik
Author-email: clickyotomy@users.noreply.github.com
License: MIT
Keywords: git .gitignore
Platform: Unix
Platform: Darwin
Classifier: Development Status :: 3 - Alpha
Classifier: Intended Audience :: Developers
Classifier: Operating System :: Unix
Classifier: Topic :: Software Development :: Build Tools
Classifier: Topic :: Software Development :: Version Control
Classifier: License :: OSI Approved :: MIT License
Classifier: Programming Language :: Python :: 2.7
Requires-Dist: requests
